fsspyipay/__init__.py
fsspyipay/exceptions.py
fsspyipay/pyipay.py
fsspyipay/util.py
fsspyipay-1.3.0.dist-info/AUTHORS.rst
fsspyipay-1.3.0.dist-info/LICENSE
fsspyipay-1.3.0.dist-info/METADATA
fsspyipay-1.3.0.dist-info/WHEEL
fsspyipay-1.3.0.dist-info/top_level.txt
fsspyipay-1.3.0.dist-info/RECORD
