Metadata-Version: 2.1
Name: fsspyipay
Version: 1.3.0
Summary: An interface for the FSS iPay terminal integration. This is the successor to the e24PaymentPipe kit which is used in Kuwait by KNET.
Home-page: https://github.com/burhan/pyipay
Author: Burhan Khalid
Author-email: burhan.khalid@gmail.com
License: MIT license
Keywords: knet,payments,kuwait,fss
Platform: UNKNOWN
Classifier: Development Status :: 4 - Beta
Classifier: Intended Audience :: Developers
Classifier: Environment :: Web Environment
Classifier: License :: OSI Approved :: MIT License
Classifier: Natural Language :: English
Classifier: Programming Language :: Python :: 3 :: Only
Classifier: Programming Language :: Python :: 3.6
Classifier: Programming Language :: Python :: 3.7
Requires-Dist: pyDes
Requires-Dist: pyjks
Requires-Dist: iso4217
